valdemar/__init__.py
valdemar/animate.py
valdemar/color.py
valdemar/discord.py
valdemar-0.0.6.dist-info/METADATA
valdemar-0.0.6.dist-info/WHEEL
valdemar-0.0.6.dist-info/top_level.txt
valdemar-0.0.6.dist-info/RECORD
